runregistry/__init__.py
runregistry/_version.py
runregistry/attributes.py
runregistry/runregistry.py
runregistry/utils.py
runregistry-3.1.2.dist-info/licenses/LICENSE
runregistry-3.1.2.dist-info/METADATA
runregistry-3.1.2.dist-info/WHEEL
runregistry-3.1.2.dist-info/top_level.txt
runregistry-3.1.2.dist-info/RECORD
