Metadata-Version: 2.4
Name: runregistry
Version: 3.1.2
Summary: CMS Run Registry client.
Author-email: Fabio Espinosa <f.e@cern.ch>
Maintainer-email: CMS PPD Technical Support <cms-PPD-technical-support@cern.ch>
Classifier: Programming Language :: Python :: 3.9
Classifier: Programming Language :: Python :: 3.10
Classifier: Programming Language :: Python :: 3.11
Classifier: Programming Language :: Python :: 3.12
Classifier: Development Status :: 5 - Production/Stable
Requires-Python: >=3.9
License-File: LICENSE
Requires-Dist: requests<3.0,>=2.18.0
Requires-Dist: cernrequests>=0.4.1
Requires-Dist: python-dotenv<2.0,>=1.0.0
Dynamic: license-file
